MANIFEST.in
README.md
setup.py
VideoLoader.egg-info/PKG-INFO
VideoLoader.egg-info/SOURCES.txt
VideoLoader.egg-info/dependency_links.txt
VideoLoader.egg-info/requires.txt
VideoLoader.egg-info/top_level.txt
videoloader/__init__.py
videoloader/_ext/AVFilterGraph.cpp
videoloader/_ext/AVFilterGraph.h
videoloader/_ext/AVFormat.cpp
videoloader/_ext/AVFormat.h
videoloader/_ext/CMakeLists.txt
videoloader/_ext/FileIO.cpp
videoloader/_ext/FileIO.h
videoloader/_ext/PyRef.cpp
videoloader/_ext/PyRef.h
videoloader/_ext/VideoDLPack.cpp
videoloader/_ext/VideoDLPack.h
videoloader/_ext/av_utils.cpp
videoloader/_ext/av_utils.h
videoloader/_ext/index.cpp
videoloader/_ext/main.cpp
videoloader/_ext/videoloader.cpp
videoloader/_ext/videoloader.h
videoloader/_ext/CMakeModules/FindAvCodec.cmake
videoloader/_ext/CMakeModules/FindAvFilter.cmake
videoloader/_ext/CMakeModules/FindAvFormat.cmake
videoloader/_ext/CMakeModules/FindAvUtil.cmake
videoloader/_ext/CMakeModules/FindFFmpegComponent.cmake
videoloader/_ext/third_party/dlpack.h